[
    {
        "key": "group_687ab04639e36",
        "title": "MQL5 Reviews",
        "fields": [
            {
                "key": "field_687ab04650fc9",
                "label": "Review 1 Name",
                "name": "review_1_name",
                "aria-label": "",
                "type": "text",
                "instructions": "",
                "required": 0,
                "conditional_logic": 0,
                "wrapper": {
                    "width": "",
                    "class": "",
                    "id": ""
                },
                "default_value": "",
                "maxlength": "",
                "allow_in_bindings": 0,
                "placeholder": "",
                "prepend": "",
                "append": ""
            },
            {
                "key": "field_687ab05550fca",
                "label": "Review 1 Date",
                "name": "review_1_date",
                "aria-label": "",
                "type": "date_picker",
                "instructions": "",
                "required": 0,
                "conditional_logic": 0,
                "wrapper": {
                    "width": "",
                    "class": "",
                    "id": ""
                },
                "display_format": "d\/m\/Y",
                "return_format": "Y-m-d",
                "first_day": 1,
                "allow_in_bindings": 0
            },
            {
                "key": "field_687ab05b50fcb",
                "label": "Review 1 Stars",
                "name": "review_1_stars",
                "aria-label": "",
                "type": "number",
                "instructions": "",
                "required": 0,
                "conditional_logic": 0,
                "wrapper": {
                    "width": "",
                    "class": "",
                    "id": ""
                },
                "default_value": "",
                "min": 1,
                "max": 5,
                "allow_in_bindings": 0,
                "placeholder": "",
                "step": "",
                "prepend": "",
                "append": ""
            },
            {
                "key": "field_687ab09950fcc",
                "label": "Review 1 Text",
                "name": "review_1_text",
                "aria-label": "",
                "type": "textarea",
                "instructions": "",
                "required": 0,
                "conditional_logic": 0,
                "wrapper": {
                    "width": "",
                    "class": "",
                    "id": ""
                },
                "default_value": "",
                "maxlength": "",
                "allow_in_bindings": 0,
                "rows": "",
                "placeholder": "",
                "new_lines": ""
            },
            {
                "key": "field_687ab0ec50fcf",
                "label": "Review 2 Name",
                "name": "review_2_name",
                "aria-label": "",
                "type": "text",
                "instructions": "",
                "required": 0,
                "conditional_logic": 0,
                "wrapper": {
                    "width": "",
                    "class": "",
                    "id": ""
                },
                "default_value": "",
                "maxlength": "",
                "allow_in_bindings": 0,
                "placeholder": "",
                "prepend": "",
                "append": ""
            },
            {
                "key": "field_687ab11c50fd3",
                "label": "Review 2 Date",
                "name": "review_2_date",
                "aria-label": "",
                "type": "date_picker",
                "instructions": "",
                "required": 0,
                "conditional_logic": 0,
                "wrapper": {
                    "width": "",
                    "class": "",
                    "id": ""
                },
                "display_format": "d\/m\/Y",
                "return_format": "Y-m-d",
                "first_day": 1,
                "allow_in_bindings": 0
            },
            {
                "key": "field_687ab13a50fd7",
                "label": "Review 2 Stars",
                "name": "review_2_stars",
                "aria-label": "",
                "type": "number",
                "instructions": "",
                "required": 0,
                "conditional_logic": 0,
                "wrapper": {
                    "width": "",
                    "class": "",
                    "id": ""
                },
                "default_value": "",
                "min": 1,
                "max": 5,
                "allow_in_bindings": 0,
                "placeholder": "",
                "step": "",
                "prepend": "",
                "append": ""
            },
            {
                "key": "field_687ab15850fdb",
                "label": "Review 2 Text",
                "name": "review_2_text",
                "aria-label": "",
                "type": "textarea",
                "instructions": "",
                "required": 0,
                "conditional_logic": 0,
                "wrapper": {
                    "width": "",
                    "class": "",
                    "id": ""
                },
                "default_value": "",
                "maxlength": "",
                "allow_in_bindings": 0,
                "rows": "",
                "placeholder": "",
                "new_lines": ""
            },
            {
                "key": "field_687ab0f850fd0",
                "label": "Review 3 Name",
                "name": "review_3_name",
                "aria-label": "",
                "type": "text",
                "instructions": "",
                "required": 0,
                "conditional_logic": 0,
                "wrapper": {
                    "width": "",
                    "class": "",
                    "id": ""
                },
                "default_value": "",
                "maxlength": "",
                "allow_in_bindings": 0,
                "placeholder": "",
                "prepend": "",
                "append": ""
            },
            {
                "key": "field_687ab12450fd4",
                "label": "Review 3 Date",
                "name": "review_3_date",
                "aria-label": "",
                "type": "date_picker",
                "instructions": "",
                "required": 0,
                "conditional_logic": 0,
                "wrapper": {
                    "width": "",
                    "class": "",
                    "id": ""
                },
                "display_format": "d\/m\/Y",
                "return_format": "Y-m-d",
                "first_day": 1,
                "allow_in_bindings": 0
            },
            {
                "key": "field_687ab14350fd8",
                "label": "Review 3 Stars",
                "name": "review_3_stars",
                "aria-label": "",
                "type": "number",
                "instructions": "",
                "required": 0,
                "conditional_logic": 0,
                "wrapper": {
                    "width": "",
                    "class": "",
                    "id": ""
                },
                "default_value": "",
                "min": 1,
                "max": 5,
                "allow_in_bindings": 0,
                "placeholder": "",
                "step": "",
                "prepend": "",
                "append": ""
            },
            {
                "key": "field_687ab16050fdc",
                "label": "Review 3 Text",
                "name": "review_3_text",
                "aria-label": "",
                "type": "textarea",
                "instructions": "",
                "required": 0,
                "conditional_logic": 0,
                "wrapper": {
                    "width": "",
                    "class": "",
                    "id": ""
                },
                "default_value": "",
                "maxlength": "",
                "allow_in_bindings": 0,
                "rows": "",
                "placeholder": "",
                "new_lines": ""
            },
            {
                "key": "field_687ab10450fd1",
                "label": "Review 4 Name",
                "name": "review_4_name",
                "aria-label": "",
                "type": "text",
                "instructions": "",
                "required": 0,
                "conditional_logic": 0,
                "wrapper": {
                    "width": "",
                    "class": "",
                    "id": ""
                },
                "default_value": "",
                "maxlength": "",
                "allow_in_bindings": 0,
                "placeholder": "",
                "prepend": "",
                "append": ""
            },
            {
                "key": "field_687ab12b50fd5",
                "label": "Review 4 Date",
                "name": "review_4_date",
                "aria-label": "",
                "type": "date_picker",
                "instructions": "",
                "required": 0,
                "conditional_logic": 0,
                "wrapper": {
                    "width": "",
                    "class": "",
                    "id": ""
                },
                "display_format": "d\/m\/Y",
                "return_format": "Y-m-d",
                "first_day": 1,
                "allow_in_bindings": 0
            },
            {
                "key": "field_687ab14a50fd9",
                "label": "Review 4 Stars",
                "name": "review_4_stars",
                "aria-label": "",
                "type": "number",
                "instructions": "",
                "required": 0,
                "conditional_logic": 0,
                "wrapper": {
                    "width": "",
                    "class": "",
                    "id": ""
                },
                "default_value": "",
                "min": 1,
                "max": 5,
                "allow_in_bindings": 0,
                "placeholder": "",
                "step": "",
                "prepend": "",
                "append": ""
            },
            {
                "key": "field_687ab16650fdd",
                "label": "Review 4 Text",
                "name": "review_4_text",
                "aria-label": "",
                "type": "textarea",
                "instructions": "",
                "required": 0,
                "conditional_logic": 0,
                "wrapper": {
                    "width": "",
                    "class": "",
                    "id": ""
                },
                "default_value": "",
                "maxlength": "",
                "allow_in_bindings": 0,
                "rows": "",
                "placeholder": "",
                "new_lines": ""
            },
            {
                "key": "field_687ab10d50fd2",
                "label": "Review 5 Name",
                "name": "review_5_name",
                "aria-label": "",
                "type": "text",
                "instructions": "",
                "required": 0,
                "conditional_logic": 0,
                "wrapper": {
                    "width": "",
                    "class": "",
                    "id": ""
                },
                "default_value": "",
                "maxlength": "",
                "allow_in_bindings": 0,
                "placeholder": "",
                "prepend": "",
                "append": ""
            },
            {
                "key": "field_687ab13350fd6",
                "label": "Review 5 Date",
                "name": "review_5_date",
                "aria-label": "",
                "type": "date_picker",
                "instructions": "",
                "required": 0,
                "conditional_logic": 0,
                "wrapper": {
                    "width": "",
                    "class": "",
                    "id": ""
                },
                "display_format": "d\/m\/Y",
                "return_format": "Y-m-d",
                "first_day": 1,
                "allow_in_bindings": 0
            },
            {
                "key": "field_687ab15150fda",
                "label": "Review 5 Stars",
                "name": "review_5_stars",
                "aria-label": "",
                "type": "number",
                "instructions": "",
                "required": 0,
                "conditional_logic": 0,
                "wrapper": {
                    "width": "",
                    "class": "",
                    "id": ""
                },
                "default_value": "",
                "min": 1,
                "max": 5,
                "allow_in_bindings": 0,
                "placeholder": "",
                "step": "",
                "prepend": "",
                "append": ""
            },
            {
                "key": "field_687ab16d50fde",
                "label": "Review 5 Text",
                "name": "review_5_text",
                "aria-label": "",
                "type": "textarea",
                "instructions": "",
                "required": 0,
                "conditional_logic": 0,
                "wrapper": {
                    "width": "",
                    "class": "",
                    "id": ""
                },
                "default_value": "",
                "maxlength": "",
                "allow_in_bindings": 0,
                "rows": "",
                "placeholder": "",
                "new_lines": ""
            },
            {
                "key": "field_687ab179a9286",
                "label": "MQL5 Total Reviews",
                "name": "mql5_total_reviews",
                "aria-label": "",
                "type": "number",
                "instructions": "",
                "required": 0,
                "conditional_logic": 0,
                "wrapper": {
                    "width": "",
                    "class": "",
                    "id": ""
                },
                "default_value": "",
                "min": "",
                "max": "",
                "allow_in_bindings": 0,
                "placeholder": "",
                "step": "",
                "prepend": "",
                "append": ""
            },
            {
                "key": "field_687ab189a9287",
                "label": "MQL5 Average Rating",
                "name": "mql5_average_rating",
                "aria-label": "",
                "type": "number",
                "instructions": "",
                "required": 0,
                "conditional_logic": 0,
                "wrapper": {
                    "width": "",
                    "class": "",
                    "id": ""
                },
                "default_value": "",
                "min": "",
                "max": "",
                "allow_in_bindings": 0,
                "placeholder": "",
                "step": "0.1",
                "prepend": "",
                "append": ""
            }
        ],
        "location": [
            [
                {
                    "param": "post_type",
                    "operator": "==",
                    "value": "product"
                }
            ]
        ],
        "menu_order": 0,
        "position": "normal",
        "style": "default",
        "label_placement": "top",
        "instruction_placement": "label",
        "hide_on_screen": "",
        "active": true,
        "description": "",
        "show_in_rest": 0
    }
]
